arbalister/__init__.py
arbalister/_version.py
arbalister/adbc.py
arbalister/arrow.py
arbalister/file_format.py
arbalister/params.py
arbalister/routes.py
arbalister/tests/__init__.py
arbalister/tests/test_params.py
arbalister/tests/test_routes.py
arbalister-0.2.0.data/data/etc/jupyter/jupyter_server_config.d/arbalister.json
arbalister-0.2.0.data/data/share/jupyter/labextensions/arbalister/package.json
arbalister-0.2.0.data/data/share/jupyter/labextensions/arbalister/static/579.96b96f40ab2557bdd276.js
arbalister-0.2.0.data/data/share/jupyter/labextensions/arbalister/static/728.8213ab3b5328faecff3b.js
arbalister-0.2.0.data/data/share/jupyter/labextensions/arbalister/static/815.f74ce31b1b97b89e64b1.js
arbalister-0.2.0.data/data/share/jupyter/labextensions/arbalister/static/remoteEntry.b36848c3d475888661d6.js
arbalister-0.2.0.data/data/share/jupyter/labextensions/arbalister/static/style.js
arbalister-0.2.0.data/data/share/jupyter/labextensions/arbalister/static/third-party-licenses.json
arbalister-0.2.0.data/data/share/jupyter/labextensions/arbalister/install.json
arbalister-0.2.0.dist-info/METADATA
arbalister-0.2.0.dist-info/WHEEL
arbalister-0.2.0.dist-info/licenses/LICENSE
arbalister-0.2.0.dist-info/RECORD
