Metadata-Version: 2.4
Name: arbalister
Version: 0.2.0
Summary: Arrow viewer for Jupyter
Project-URL: Homepage, https://github.com/QuantStack/Arbalister
Project-URL: Bug Tracker, https://github.com/QuantStack/Arbalister/issues
Project-URL: Repository, https://github.com/QuantStack/Arbalister
Author-email: AntoinePrv <AntoinePrv@users.noreply.github.com>
License: BSD 3-Clause License
License-File: LICENSE
Keywords: jupyter,jupyterlab,jupyterlab-extension
Classifier: Framework :: Jupyter
Classifier: Framework :: Jupyter :: JupyterLab
Classifier: Framework :: Jupyter :: JupyterLab :: 4
Classifier: Framework :: Jupyter :: JupyterLab :: Extensions
Classifier: Framework :: Jupyter :: JupyterLab :: Extensions :: Prebuilt
Classifier: License :: OSI Approved :: BSD License
Classifier: Programming Language :: Python
Classifier: Programming Language :: Python :: 3
Classifier: Programming Language :: Python :: 3.12
Classifier: Programming Language :: Python :: 3.13
Classifier: Programming Language :: Python :: 3.14
Requires-Python: >=3.9
Requires-Dist: adbc-driver-manager
Requires-Dist: adbc-driver-sqlite
Requires-Dist: datafusion>=40.0
Requires-Dist: jupyter-server<3,>=2.4.0
Requires-Dist: pyarrow>=20.0
